{
    "os": "Windows-10-10.0.22631-SP0",
    "python": "3.8.19",
    "heartbeatAt": "2024-05-02T08:12:54.743243",
    "startedAt": "2024-05-02T08:12:52.390834",
    "docker": null,
    "gpu": "NVIDIA GeForce RTX 3060",
    "gpu_count": 1,
    "cpu_count": 12,
    "cuda": null,
    "args": [
        "--f=c:\\Users\\USER\\AppData\\Roaming\\jupyter\\runtime\\kernel-v2-13136OacFa6i5PU5j.json"
    ],
    "state": "running",
    "program": "<python with no main file>",
    "host": "DESKTOP-QNHRJP5",
    "username": "USER",
    "executable": "c:\\Users\\USER\\anaconda3\\envs\\key_bert\\python.exe"
}
